README.md
setup.py
flowbase/__init__.py
flowbase/flowbase.py
flowbase.egg-info/PKG-INFO
flowbase.egg-info/SOURCES.txt
flowbase.egg-info/dependency_links.txt
flowbase.egg-info/top_level.txt