Metadata-Version: 2.1
Name: flowbase
Version: 0.0.3
Summary: Python implementation of the FlowBase Flow-based Programming micro-framework idea (see flowbase.org)
Home-page: https://github.com/flowbase/flowbase-python
Author: Samuel Lampa
Author-email: samuel.lampa@rilnet.com
License: MIT
Keywords: flow-based programming
Platform: UNKNOWN
Classifier: Development Status :: 3 - Alpha
Classifier: Environment :: Console
Classifier: Intended Audience :: Science/Research
Classifier: License :: OSI Approved :: MIT License
Classifier: Natural Language :: English
Classifier: Operating System :: POSIX :: Linux
Classifier: Programming Language :: Python
Classifier: Programming Language :: Python :: 3.5
